{
    "projects": [{
        "id": "pipper",
        "title": "Pipper",
        "description": "Lorem ipsum dolor sit amet, <a href='#'><img border='0' alt='email' src='mail.svg' width='32' height='32'></a> consectetur adipiscing elit. Quisque in risus sollicitudin, sodales eros vitae.",
        "category": "fullstack",
        "icons": ["rails", "angular", "bootstrap"],
        "links" : {
            "Try" : "http://www.test1.com",
            "Source code" : "http://www.test2.com"
        }
    }, {
        "id": "saas",
        "title": "SaaS",
        "description": "Lorem ipsum dolor sit amet, consectetur adipiscing elit. Quisque in risus sollicitudin, sodales eros vitae. Lorem ipsum dolor sit amet, consectetur adipiscing elit. Quisque in risus sollicitudin, sodales eros vitae.",
        "category": "webdesign",
        "icons": [],
        "links" : {
            "Try" : "http://www.test1.com",
            "Source code" : "http://www.test2.com"
        }
    }, {
        "id": "tictactoeai",
        "title": "TicTacToe-AI",
        "description": "Lorem ipsum dolor sit amet, consectetur adipiscing elit. Quisque in risus sollicitudin, sodales eros vitae.",
        "category": "experiments",
        "icons": [],
        "links" : {
            "Try" : "http://www.test1.com",
            "Source code" : "http://www.test2.com"
        }
    }, {
        "id": "softwarerenderer",
        "title": "Software Renderer",
        "description": "Lorem ipsum dolor sit amet, consectetur adipiscing elit. Quisque in risus sollicitudin, sodales eros vitae. Lorem ipsum dolor sit amet, consectetur adipiscing elit. Quisque in risus sollicitudin, sodales eros vitae. Lorem ipsum dolor sit amet, consectetur adipiscing elit. Quisque in risus sollicitudin, sodales eros vitae.",
        "category": "experiments",
        "icons": [],
        "links" : {
            "Try" : "http://www.test1.com",
            "Source code" : "http://www.test2.com"
        }
    }, {
        "id": "pixelrush",
        "title": "Pixel Rush",
        "description": "Lorem ipsum dolor sit amet, consectetur adipiscing elit. Quisque in risus sollicitudin, sodales eros vitae.",
        "category": "games",
        "icons": [],
        "links" : {
            "App Store" : "http://www.test1.com",
            "Google Play" : "http://www.test2.com"
        }
    }, {
        "id": "vanished",
        "title": "Vanished",
        "description": "consectetur adipiscing elit. Quisque in risus sollicitudin, sodales eros vitae. Lorem ipsum dolor sit amet, consectetur adipiscing elit. Quisque in risus sollicitudin, sodales eros vitae. Lorem ipsum dolor sit amet, consectetur adipiscing elit. Quisqu Lorem ipsum dolor sit amet, consectetur adipiscing elit. Quisque in risus sollicitudin, sodales eros vitae.",
        "category": "games",
        "icons": [],
        "links" : {
            "App Store" : "http://www.test1.com",
            "Google Play" : "http://www.test2.com"
        }
    }, {
        "id": "hypermazearcade",
        "title": "Hyper Maze Arcade",
        "description": "Hyper Maze Arcade is the evolution of the classic maze game. It's a new type of game that takes inspiration from a classic game concept and innovates it to a whole new level.",
        "category": "games",
        "icons": [],
        "links" : {
            "App Store" : "http://itunes.apple.com/app/id947001459",
            "Google Play" : "https://play.google.com/store/apps/details?id=com.pixelheartstudios.hypermaze"
        }
    }, {
        "id": "evilcupido",
        "title": "Evil Cupido",
        "description": "A game developed in 3 days for the Ludum Dare 32 competition.",
        "category": "games",
        "icons": [],
        "links" : {
        }
    }]
}
